[
    {
        "key": "dbln",
        "value": "%7B%22100070022195809%22%3A%22WYVr11y3%22%2C%2261567886176425%22%3A%22P698XpCB%22%2C%2261570039482724%22%3A%22zQgwPnh9%22%7D",
        "domain": "facebook.com",
        "path": "/login/device-based/",
        "hostOnly": false,
        "creation": "2024-12-15T02:34:29.934Z",
        "lastAccessed": "2024-12-15T02:34:29.954Z"
    },
    {
        "key": "sb",
        "value": "4T_9Zr41wnJ2bkCtFGtg6sPg",
        "domain": "facebook.com",
        "path": "/",
        "hostOnly": false,
        "creation": "2024-12-15T02:34:29.954Z",
        "lastAccessed": "2024-12-15T02:34:29.954Z"
    },
    {
        "key": "datr",
        "value": "p1IsZxf26EdIiFwcqZ1ZL-QE",
        "domain": "facebook.com",
        "path": "/",
        "hostOnly": false,
        "creation": "2024-12-15T02:34:29.954Z",
        "lastAccessed": "2024-12-15T02:34:29.954Z"
    },
    {
        "key": "vpd",
        "value": "v1%3B702x360x2",
        "domain": "facebook.com",
        "path": "/",
        "hostOnly": false,
        "creation": "2024-12-15T02:34:29.954Z",
        "lastAccessed": "2024-12-15T02:34:29.954Z"
    },
    {
        "key": "dpr",
        "value": "2",
        "domain": "facebook.com",
        "path": "/",
        "hostOnly": false,
        "creation": "2024-12-15T02:34:29.954Z",
        "lastAccessed": "2024-12-15T02:34:29.954Z"
    },
    {
        "key": "m_pixel_ratio",
        "value": "2",
        "domain": "facebook.com",
        "path": "/",
        "hostOnly": false,
        "creation": "2024-12-15T02:34:29.954Z",
        "lastAccessed": "2024-12-15T02:34:29.954Z"
    },
    {
        "key": "wd",
        "value": "360x702",
        "domain": "facebook.com",
        "path": "/",
        "hostOnly": false,
        "creation": "2024-12-15T02:34:29.954Z",
        "lastAccessed": "2024-12-15T02:34:29.954Z"
    },
    {
        "key": "c_user",
        "value": "61570039482724",
        "domain": "facebook.com",
        "path": "/",
        "hostOnly": false,
        "creation": "2024-12-15T02:34:29.954Z",
        "lastAccessed": "2024-12-15T02:34:29.954Z"
    },
    {
        "key": "fr",
        "value": "1Hf2H3yZmL9vurFbO.AWXU3HYlaSY1Og22ggzzqsPOuyY.BnXZFi..AAA.0.0.BnXj62.AWXMYXBvMBU",
        "domain": "facebook.com",
        "path": "/",
        "hostOnly": false,
        "creation": "2024-12-15T02:34:29.954Z",
        "lastAccessed": "2024-12-15T02:34:29.954Z"
    },
    {
        "key": "xs",
        "value": "17%3ArlN9nydKLH1hAw%3A2%3A1734229688%3A-1%3A-1",
        "domain": "facebook.com",
        "path": "/",
        "hostOnly": false,
        "creation": "2024-12-15T02:34:29.954Z",
        "lastAccessed": "2024-12-15T02:34:29.955Z"
    },
    {
        "key": "locale",
        "value": "en_GB",
        "domain": "facebook.com",
        "path": "/",
        "hostOnly": false,
        "creation": "2024-12-15T02:34:29.955Z",
        "lastAccessed": "2024-12-15T02:34:29.955Z"
    },
    {
        "key": "fbl_st",
        "value": "100637813%3BT%3A28903828",
        "domain": "facebook.com",
        "path": "/",
        "hostOnly": false,
        "creation": "2024-12-15T02:34:29.955Z",
        "lastAccessed": "2024-12-15T02:34:29.955Z"
    },
    {
        "key": "wl_cbv",
        "value": "v2%3Bclient_version%3A2696%3Btimestamp%3A1734229695",
        "domain": "facebook.com",
        "path": "/",
        "hostOnly": false,
        "creation": "2024-12-15T02:34:29.955Z",
        "lastAccessed": "2024-12-15T02:34:29.955Z"
    }
]
